anydoc/__init__.py
anydoc/py.typed
anydoc-0.0.0.dist-info/METADATA
anydoc-0.0.0.dist-info/WHEEL
anydoc-0.0.0.dist-info/licenses/LICENSE
anydoc-0.0.0.dist-info/RECORD
